kamer/__main__.py
kamer/bus.py
kamer/command.py
kamer/define.py
kamer/error.py
kamer/event.py
kamer/json.py
kamer/locks.py
kamer/object.py
kamer/parser.py
kamer/persist.py
kamer/reactor.py
kamer/repeater.py
kamer/run.py
kamer/thread.py
kamer/utils.py
kamer/modules/__init__.py
kamer/modules/cmd.py
kamer/modules/dbg.py
kamer/modules/err.py
kamer/modules/flt.py
kamer/modules/irc.py
kamer/modules/log.py
kamer/modules/mdl.py
kamer/modules/mod.py
kamer/modules/req.py
kamer/modules/rss.py
kamer/modules/shp.py
kamer/modules/sts.py
kamer/modules/tdo.py
kamer/modules/thr.py
kamer/modules/udp.py
kamer/modules/wsd.py
kamer-51.data/data/share/doc/kamer/about.rst
kamer-51.data/data/share/doc/kamer/bewijsgif4.jpg
kamer-51.data/data/share/doc/kamer/conf.py
kamer-51.data/data/share/doc/kamer/index.rst
kamer-51.data/data/share/doc/kamer/manual.rst
kamer-51.data/data/share/doc/kamer/robots.txt
kamer-51.data/data/share/doc/kamer/skull.png
kamer-51.data/data/share/doc/kamer/source.rst
kamer-51.data/data/share/doc/kamer/tochamber.rst
kamer-51.data/data/share/doc/kamer/_static/kamer.css
kamer-51.data/data/share/doc/kamer/_templates/base.rst
kamer-51.data/data/share/doc/kamer/_templates/class.rst
kamer-51.data/data/share/doc/kamer/_templates/module.rst
kamer-51.data/data/share/doc/kamer/jpg/20140730_011.jpg
kamer-51.data/data/share/doc/kamer/jpg/20151029_004.jpg
kamer-51.data/data/share/doc/kamer/jpg/ECHAhaloperidol.png
kamer-51.data/data/share/doc/kamer/jpg/aes.ico
kamer-51.data/data/share/doc/kamer/jpg/beuker2.jpg
kamer-51.data/data/share/doc/kamer/jpg/bevestigd.jpg
kamer-51.data/data/share/doc/kamer/jpg/bevestigd3.jpg
kamer-51.data/data/share/doc/kamer/jpg/bewijsgif3.jpg
kamer-51.data/data/share/doc/kamer/jpg/bewijsgif4.jpg
kamer-51.data/data/share/doc/kamer/jpg/fact.jpg
kamer-51.data/data/share/doc/kamer/jpg/igz.jpg
kamer-51.data/data/share/doc/kamer/jpg/nederland2.jpg
kamer-51.data/data/share/doc/kamer/jpg/stoned2.jpg
kamer-51.data/data/share/doc/kamer/pdf/bevestigd.pdf
kamer-51.dist-info/METADATA
kamer-51.dist-info/WHEEL
kamer-51.dist-info/entry_points.txt
kamer-51.dist-info/top_level.txt
kamer-51.dist-info/zip-safe
kamer-51.dist-info/RECORD
