Metadata-Version: 2.1
Name: kamer
Version: 51
Summary: ANTIPSYCHOTICA - AKATHISIA - KATATONIE - SEDERING - SHOCKS - LETHALE KATATONIE
Author-email: Bart Thate <bthate@dds.nl>
License: Public Domain
Project-URL: home, https://pypi.org/project/kamer
Project-URL: bugs, https://github.com/bthate/kamer/issues
Project-URL: source, https://github.com/bthate/kamer
Classifier: Development Status :: 3 - Alpha
Classifier: License :: Public Domain
Classifier: Operating System :: Unix
Classifier: Programming Language :: Python
Classifier: Topic :: Utilities
Provides-Extra: dev
